LICENSE
notification/__init__.py
notification/admin.py
notification/app_settings.py
notification/apps.py
notification/backends/__init__.py
notification/backends/aliyunsms.py
notification/backends/dingchatbot.py
notification/backends/dingtodotask.py
notification/backends/dingworkmessage.py
notification/backends/dummy.py
notification/backends/email.py
notification/backends/websocket.py
notification/base.py
notification/consumers.py
notification/migrations/0001_initial.py
notification/migrations/0002_auto_20220808_0736.py
notification/migrations/0003_auto_20220810_1710.py
notification/migrations/0004_auto_20220812_0705.py
notification/migrations/0005_alter_message_id_alter_messagetemplate_id_and_more.py
notification/migrations/__init__.py
notification/models.py
notification/static/css/hide_admin_original.css
notification/urls.py
notification/utils.py
django_user_notification-0.10.2.dist-info/LICENSE
django_user_notification-0.10.2.dist-info/METADATA
django_user_notification-0.10.2.dist-info/WHEEL
django_user_notification-0.10.2.dist-info/RECORD
