Metadata-Version: 2.1
Name: django-user-notification
Version: 0.10.2
Summary: Django message notification package
Home-page: https://github.com/aiden520/django-user-notification
License: Apache-2.0
Keywords: notification,django
Author: Aiden Lu
Author-email: allaher@icloud.com
Requires-Python: >=3.8
Classifier: Environment :: Web Environment
Classifier: Intended Audience :: Developers
Classifier: License :: OSI Approved :: Apache Software License
Classifier: Programming Language :: Python :: 3
Classifier: Programming Language :: Python :: 3.8
Classifier: Programming Language :: Python :: 3.9
Classifier: Programming Language :: Python :: 3.10
Classifier: Programming Language :: Python :: 3.11
Classifier: Topic :: Software Development :: Libraries :: Python Modules
Provides-Extra: aliyunsms
Provides-Extra: channels
Requires-Dist: alibabacloud-dysmsapi20170525 (>=2.0.16) ; extra == "aliyunsms"
Requires-Dist: channels (>=3.0.4) ; extra == "channels"
Requires-Dist: django (>=3.1)
Requires-Dist: django-tinymce (>=3.6.1,<4.0.0)
Requires-Dist: markdownify (>=0.11.2)
Requires-Dist: requests (>=2.27.1,<3.0.0)
Project-URL: Repository, https://github.com/aiden520/django-user-notification
